logik/__init__.py
logik/devices/__init__.py
logik/devices/logik_fpga.py
logik/flows/__init__.py
logik/flows/logik_flow.py
logik/tools/__init__.py
logik/tools/fasm_to_bitstream/__init__.py
logik/tools/fasm_to_bitstream/bitstream_bin_convert.py
logik/tools/fasm_to_bitstream/bitstream_finish.py
logik/tools/fasm_to_bitstream/fasm_to_bitstream.py
logik-0.2.0.dist-info/licenses/LICENSE
logik-0.2.0.dist-info/METADATA
logik-0.2.0.dist-info/WHEEL
logik-0.2.0.dist-info/top_level.txt
logik-0.2.0.dist-info/RECORD
