Metadata-Version: 2.4
Name: logik
Version: 0.2.0
Summary: Logik is a light weight FPGA tool chain based on mature open source technologies.
Author: Zero ASIC
License:                                  Apache License
Project-URL: Homepage, https://github.com/siliconcompiler/logik
Requires-Python: >=3.8
License-File: LICENSE
Requires-Dist: logiklib==0.2.0
Requires-Dist: siliconcompiler>=0.35.1
Provides-Extra: test
Requires-Dist: pytest==8.4.2; extra == "test"
Requires-Dist: pytest-timeout==2.4.0; extra == "test"
Requires-Dist: flake8==7.3.0; extra == "test"
Provides-Extra: docs
Requires-Dist: Sphinx==8.2.3; extra == "docs"
Requires-Dist: sphinx-rtd-theme==3.0.2; extra == "docs"
Requires-Dist: autodocsumm==0.2.14; extra == "docs"
Dynamic: license-file
